{"intent_actions": ["android.intent.action.MAIN", "com.android.ussd.IExtendedNetworkService", "android.provider.Telephony.SMS_RECEIVED", "android.intent.action.BOOT_COMPLETED", "android.intent.action.USER_PRESENT", "android.intent.action.PACKAGE_REMOVED", "android.intent.action.PACKAGE_ADDED", "com.google.android.c2dm.intent.RECEIVE", "android.app.action.DEVICE_ADMIN_ENABLED", "android.app.action.DEVICE_ADMIN_DISABLED", "android.app.action.DEVICE_ADMIN_DISABLE_REQUESTED", "android.intent.action.PACKAGE_REMOVED", "android.intent.action.PACKAGE_ADDED", "android.intent.action.BOOT_COMPLETED"], "num_permissions": 30, "intent_consts": ["'android.intent.action.MAIN'", "'android.intent.category.HOME'", "'android.intent.action.PACKAGE_REMOVED'", "'android.intent.action.PACKAGE_ADDED'", "'android.intent.action.DELETE'", "'android.intent.action.DELETE'", "'android.intent.action.VIEW'", "'android.intent.action.MAIN'", "'android.intent.category.HOME'", "'com.google.android.c2dm.intent.REGISTER'", "'android.intent.action.SCREEN_ON'", "'android.intent.action.SCREEN_OFF'", "'android.intent.action.VIEW'", "'android.intent.action.CALL'", "'android.intent.action.VIEW'", "'android.intent.extra.shortcut.INTENT'", "'android.intent.extra.shortcut.NAME'", "'android.intent.extra.shortcut.ICON'", "'android.intent.action.VIEW'", "'android.intent.action.PACKAGE_REMOVED'", "'android.intent.action.NEW_OUTGOING_CALL'", "'android.intent.extra.PHONE_NUMBER'", "'android.intent.action.BOOT_COMPLETED'", "'android.intent.action.PACKAGE_ADDED'", "'android.intent.action.USER_PRESENT'", "'android.intent.action.SCREEN_ON'", "'android.intent.action.SCREEN_OFF'"], "num_intent_const_android_intent": 20, "used_permissions": {"android.permission.ACCESS_FINE_LOCATION": 3, "android.permission.SEND_SMS": 2, "android.permission.READ_PHONE_STATE": 3, "android.permission.VIBRATE": 1, "android.permission.ACCESS_NETWORK_STATE": 9, "android.permission.ACCESS_COARSE_LOCATION": 3, "android.permission.WAKE_LOCK": 4, "android.permission.GET_TASKS": 1, "android.permission.INTERNET": 8, "android.permission.READ_CONTACTS": 2, "android.permission.WRITE_CONTACTS": 2}, "su": 1, "file": {"DEX": 1, "ASCII": 5, "data": 8, "PNG": 2, "empty": 1}, "method_tags": {"UTIL": 2, "WIDGET": 10, "PROVIDER": 1, "DATABASE": 16, "TEXT": 6, "APP": 40, "JAVA_REFLECTION": 7, "SMS": 1, "CONTENT": 98, "TELEPHONY": 5, "LOCATION": 2, "GRAPHICS": 1, "WEBKIT": 11, "ANDROID": 164, "OS": 24, "NET": 16, "SMSMESSAGE": 2, "VIEW": 5}, "num_intent_action_android_intent": 8, "target_sdk": "4", "num_files": 17, "num_intent_const_other": 7, "num_libraries": 0, "num_intent_action_other": 5, "version_code": "30", "ascii_obfuscation": 0, "num_receivers": 4, "num_intent_action_com_android": 1, "num_providers": 0, "num_third_part_permissions": 4, "main_activity": "com.gamecraft.micromill.MainActivity", "receivers": ["roijf.sdfqlkj.sfakjdfa.MainReceiver", "roijf.sdfqlkj.sfakjdfa.GCMReceiver", "roijf.sdfqlkj.sfakjdfa.AdminReceiver", "antivirus.pro.MainReceiver"], "num_services": 7, "is_valid_APK": true, "services": ["roijf.sdfqlkj.sfakjdfa.MainReceiver", "roijf.sdfqlkj.sfakjdfa.GCMReceiver", "roijf.sdfqlkj.sfakjdfa.AdminReceiver", "antivirus.pro.MainReceiver"], "antagonist": 0, "permissions": ["android.permission.READ_PHONE_STATE", "android.permission.SEND_SMS", "android.permission.RECEIVE_SMS", "android.permission.WRITE_SMS", "android.permission.READ_SMS", "android.permission.INTERNET", "android.permission.DELETE_PACKAGES", "android.permission.MODIFY_PHONE_STATE", "android.permission.CALL_PHONE", "android.permission.CALL_PRIVILEGED", "android.permission.PROCESS_OUTGOING_CALLS", "android.permission.WRITE_CONTACTS", "android.permission.READ_CONTACTS", "android.permission.WRITE_EXTERNAL_STORAGE", "android.permission.RECEIVE_BOOT_COMPLETED", "com.android.launcher.permission.INSTALL_SHORTCUT", "android.permission.ACCESS_COARSE_LOCATION", "android.permission.ACCESS_FINE_LOCATION", "android.permission.ACCESS_COARSE_UPDATES", "android.permission.READ_CALL_LOG", "android.permission.AUTHENTICATE_ACCOUNTS", "android.permission.GET_ACCOUNTS", "android.permission.GET_TASKS", "android.permission.ACCESS_NETWORK_STATE", "android.permission.INSTALL_PACKAGES", "android.permission.READ_LOGS", "android.permission.DELETE_PACKAGES", "android.permission.WAKE_LOCK", "com.google.android.c2dm.permission.RECEIVE", "com.gamecraft.micromill.permission.C2D_MESSAGE"], "reflection": 5, "num_intent_actions": 14, "package": "com.gamecraft.micromill", "num_activities": 5, "sensitive_API": {"TelephonyManager:getNetworkOperator": 1, "Process:killProcess": 0, "PackageManager:getInstalledPackages": 3, "TelephonyManager:getSimSerialNumber": 0, "ActivityManager:getRunningServices": 0, "TelephonyManager:getSubscriberId": 1, "File:mkdir": 1, "Intent:setDataAndType": 1, "File:ListFiles": 0, "LocationManager:getLastKnownLocation": 0, "SmsManager:sendTextMessage": 0, "WifiManager:getConnectionInfo": 0, "Context:getFilesDir": 1, "File:exists": 3, "ContentResolver:insert": 2, "URL:openConnection": 2, "HttpURLConnection:connect": 3, "URLConnection:getInputStream": 1, "Context:getApplicationInfo": 0, "File:delete": 2, "WifiManager:getIpAddress": 0, "TelephonyManager:getCellLocation": 1, "TelephonyManager:getLine1Number": 1, "WifiManager:isWifiEnabled": 0, "TelephonyManager:getDeviceId": 1, "ConnectivityManager:getActiveNetworkInfo": 1, "ActivityManager:getMemoryInfo": 0, "ContentResolver:delete": 1, "Intent:addFlags": 15, "LocationManager:requestLocationUpdate": 1, "ContentResolver:query": 5, "Process:myPid": 0, "ActivityManager:restartPackage": 0, "Intent:setFlags": 3, "Context:openFileOuput": 0}, "dynamic_code": 0, "emulator": 3, "native_code": 0}